oximy/__init__.py
oximy/client.py
oximy/constants.py
oximy/normalizer.py
oximy/providers.py
oximy/telemetry.py
oximy/types.py
oximy/utils.py
oximy/wrapper.py
oximy/policy/__init__.py
oximy/policy/evaluator.py
oximy/policy/manager.py
oximy/policy/redaction.py
oximy/policy/stores.py
oximy-0.0.2.dist-info/METADATA
oximy-0.0.2.dist-info/WHEEL
oximy-0.0.2.dist-info/top_level.txt
oximy-0.0.2.dist-info/RECORD
